{
    "id": "1821478",
    "localized title": "Kaavalan",
    "cast": [
        "Joseph Vijay",
        "Asin Thottumkal",
        "Raj Kiran",
        "Vadivelu",
        "Roja",
        "Mithra Kurian",
        "Mahadevan",
        "Nizhalgal Ravi",
        "Krishna Kumar",
        "Livingston",
        "Neepa",
        "M.S. Bhaskar",
        "Yuvashree",
        "Madhan Bob",
        "Ajaykumar",
        "Manel Soler"
    ],
    "genres": [
        "Action",
        "Comedy",
        "Drama",
        "Romance"
    ],
    "runtimes": "155",
    "countries": "India",
    "country codes": "in",
    "language codes": "ta",
    "color info": "Color",
    "certificates": [
        "Canada:PG::(Alberta)",
        "India:U",
        "Malaysia:P13",
        "New Zealand:M",
        "United Kingdom:12A",
        "United Kingdom:12::(DVD rating)",
        "United States:Not Rated"
    ],
    "original air date": "15 Jan 2011 (India)",
    "cover url": "https://m.media-amazon.com/images/M/MV5BYTE2MzAxYWEtZTU4OC00OGI5LTlkMDQtMDhjZTdmZDIzODU1XkEyXkFqcGdeQXVyMTEzNzg0Mjkx._V1_SY150_CR4,0,101,150_.jpg",
    "imdbID": "1821478",
    "plot outline": "Bhoominathan aka Bhoomi is introduced to us as a person who gets into many local fights. Worried about his future, his family sends him to Muthuramalingam (Raj Kiran), a much respected personality in his place Semmanur, to put Bhoomi's life on the right track. But things don't go as planned. Muthuramalingam's adversary threatens to kill his daughter Meera (Asin) as a revenge against his own daughter's fate. So Bhoomi is given the job of Meera's bodyguard at college. Meera goes to college with her friend Madhu but is irritated by Bhoomi's presence everywhere. So she devises a plan.",
    "languages": "Tamil",
    "title": "Kaavalan",
    "kind": "movie",
    "directors": [
        "Siddique",
        "K.R. Gowri Shankar"
    ],
    "writers": [
        "Guruvaran",
        "",
        "Siddique"
    ],
    "producers": [
        "Ramesh Babu",
        "N. Viswanathan"
    ],
    "composers": "Vidyasagar",
    "cinematographers": "N.K. Ekambaram",
    "editors": [
        "Gowrishankar K R",
        "K.R. Gowri Shankar"
    ],
    "editorial department": "G.S. Muthu",
    "art directors": "Mani Suchithra",
    "assistant directors": [
        "Sa Baskaran",
        "Ashwin Neal Mani"
    ],
    "visual effects": [
        "Srinivasan Punniyakrishnan",
        "Selvakumar",
        "Andrew Shibi"
    ],
    "stunts": [
        "Stun Shiva",
        "Manel Soler"
    ],
    "camera department": [
        "Vanchinathan Murugesan",
        "J.D. Rama Thulasi"
    ],
    "music department": [
        "Singer Megha",
        "Vidyasagar",
        "Pa. Vijay",
        "Dharma Vish"
    ],
    "miscellaneous": [
        "Vishnu Deva",
        "Dinesh",
        "L. Muthu Karuppiah",
        "Jayaram Ramachandran",
        "Raju Sundaram",
        "V. Umapathyraju"
    ],
    "akas": "Kaavalan: The Bodyguard",
    "writer": [
        "Guruvaran",
        "Siddique"
    ],
    "director": [
        "Siddique",
        "K.R. Gowri Shankar"
    ],
    "production companies": "Ekaveera Creations",
    "distributors": [
        "Ayngaran International",
        "Cinema Paradise",
        "Ekaveera Creations",
        "Parasakthi Films",
        "Sun TV"
    ],
    "other companies": "Venus",
    "plot": [
        "Meera starts calling bhoomi, her bodyguard just to fool him by telling him she loves him. Problems arise when bhoomi falls in love with her not knowing who she is.",
        "Bhoominathan aka Bhoomi is introduced to us as a person who gets into many local fights. Worried about his future, his family sends him to Muthuramalingam (Raj Kiran), a much respected personality in his place Semmanur, to put Bhoomi's life on the right track. But things don't go as planned. Muthuramalingam's adversary threatens to kill his daughter Meera (Asin) as a revenge against his own daughter's fate. So Bhoomi is given the job of Meera's bodyguard at college. Meera goes to college with her friend Madhu but is irritated by Bhoomi's presence everywhere. So she devises a plan.::Anonymous"
    ]
}