{
    "id": "3172262",
    "localized title": "Maduve Mane",
    "cast": [
        "Ganesh",
        "Shraddha Arya",
        "Avinash",
        "Hanumanthe Gowda",
        "Tabla Nani",
        "Sharan",
        "Spoorthi Vishwas"
    ],
    "genres": [
        "Comedy",
        "Drama",
        "Romance"
    ],
    "runtimes": "131",
    "countries": "India",
    "country codes": "in",
    "language codes": "kn",
    "color info": "Color",
    "certificates": [
        "India:U",
        "United States:Not Rated"
    ],
    "cover url": "https://m.media-amazon.com/images/M/MV5BMjVhODc1ODUtNzFkOC00MzY0LWE3ZjktY2VhM2QwN2M0MWFlXkEyXkFqcGdeQXVyMzQzMDc2MDk@._V1_SY150_CR28,0,101,150_.jpg",
    "imdbID": "3172262",
    "plot outline": "Maduve Mane is a 2011 Kannada film,directed by Sunil Kumar Singh and produced by H.A.Rahman.The flim stars Ganesh,Shradha Arya in lead roles.The music of the film was composed by Manikanth Kadri.",
    "languages": "Kannada",
    "title": "Maduve Mane",
    "kind": "movie",
    "directors": "Sunil Kumar Singh",
    "producers": "H.A. Rahman",
    "composers": "Manikanth Kadri",
    "cinematographers": "Shekar Chandru",
    "production managers": "Champakadhama Babu",
    "akas": "Maduve Mane (India)",
    "director": "Sunil Kumar Singh",
    "production companies": "K Manju Cinemaas",
    "distributors": "K Manju Cinemaas",
    "plot": "_Maduve Mane_ (qv) is a 2011 Kannada film,directed by Sunil Kumar Singh and produced by H.A.Rahman.The flim stars Ganesh,Shradha Arya in lead roles.The music of the film was composed by Manikanth Kadri."
}