{
    "id": "1028558",
    "localized title": "Nadiya Kollappetta Rathri",
    "cast": [
        "Suresh Gopi",
        "Kavya Madhavan",
        "Shammi Thilakan",
        "Siddique",
        "Suraj Venjaramoodu",
        "Madhupal",
        "Suresh Krishna",
        "Suja Karthika",
        "Rajan P. Dev",
        "Urmila Unni",
        "Kollam Thulasi",
        "Anoop Chandran",
        "Bindu Panikkar",
        "Subair",
        "Vijay Menon",
        "Sajitha Beti",
        "Baburaj",
        "Prithviraj Sukumaran",
        "Joju George",
        "Vijayakumar"
    ],
    "genres": [
        "Action",
        "Crime",
        "Mystery",
        "Thriller"
    ],
    "countries": "India",
    "country codes": "in",
    "language codes": "ml",
    "color info": "Color",
    "certificates": "India:UA",
    "original air date": "27 Jul 2007 (India)",
    "cover url": "https://m.media-amazon.com/images/M/MV5BZWU4ZDNhNDktOWUwYi00YzFkLTg4NjUtYTA5NzQ0NjRlNDMyXkEyXkFqcGdeQXVyMTEzNzg0Mjkx._V1_SY150_CR3,0,101,150_.jpg",
    "imdbID": "1028558",
    "languages": "Malayalam",
    "title": "Nadiya Kollappetta Rathri",
    "kind": "movie",
    "directors": "K. Madhu",
    "writers": "A.K. Sajan",
    "producers": "K. Madhu",
    "composers": "Rajamani",
    "cinematographers": "Anandakuttan",
    "editors": "P.C. Mohanan",
    "editorial department": [
        "K. Sasi Kumar",
        "Sasi Kumar"
    ],
    "assistant directors": [
        "Relan Earnest",
        "I. Sasi"
    ],
    "sound department": "Ajith Abraham George",
    "stunts": "Mafia Sasi",
    "miscellaneous": "Vazhoor Jose",
    "thanks": [
        "Navodaya Appachan",
        "Prithviraj Sukumaran"
    ],
    "akas": "The Night Nadiya Was Murdered (United States)",
    "writer": "A.K. Sajan",
    "director": "K. Madhu",
    "plot": "Railway Anti-Criminal Task Force (RATs) investigates three unrelated murders happened in a train."
}