{
    "id": "1707233",
    "localized title": "Lad Gaya Pecha",
    "cast": [
        "Amrit",
        "Shoma Anand",
        "Rana Jung Bahadur",
        "Gopi Bhalla",
        "Ashwani Bhardwaj",
        "Gurpreet Ghuggi",
        "Alisha Grewal Khan",
        "Mk",
        "Pritti",
        "Navnit Ravi Rana",
        "Khayali Saharan"
    ],
    "genres": "Comedy",
    "runtimes": "143",
    "countries": "India",
    "country codes": "in",
    "language codes": "pa",
    "color info": "Color",
    "certificates": [
        "India:U",
        "United Kingdom:15"
    ],
    "original air date": "26 Mar 2010 (India)",
    "cover url": "https://m.media-amazon.com/images/M/MV5BMmFiMjdmMjgtM2MxMS00NDcxLTkxNTYtYmJiNGI1ODNjMzk3XkEyXkFqcGdeQXVyNjE4MTE3MDY@._V1_SY150_CR3,0,101,150_.jpg",
    "imdbID": "1707233",
    "languages": "Punjabi",
    "title": "Lad Gaya Pecha",
    "kind": "movie",
    "directors": "Anmol Arora",
    "producers": "Manoj Kumar",
    "composers": "Anmol Arora",
    "cinematographers": "Najeeb Khan",
    "editors": "Param Dhillon",
    "akas": "Lad Gaya Pecha (India)",
    "director": "Anmol Arora",
    "production companies": "Emotion Entertainment",
    "distributors": "Super Cassettes Industries Limited (T-Series)",
    "plot": "A man is trying to get married he tries to kill himself after he falls in love with a ghost and is also in love with a human being. Who Will He Choose?"
}