{
    "id": "7539210",
    "localized title": "Sangu Chakkaram",
    "cast": [
        "'Punnagai Poo' Geetha",
        "Monica",
        "Jeremy Roske",
        "Dhilip Subbarayan",
        "Pradeep K Vijayan"
    ],
    "genres": [
        "Comedy",
        "Fantasy",
        "Horror"
    ],
    "runtimes": "124",
    "countries": "India",
    "country codes": "in",
    "language codes": "ta",
    "color info": "Color",
    "certificates": [
        "India:U",
        "Singapore:PG13"
    ],
    "original air date": "29 Dec 2017 (India)",
    "cover url": "https://m.media-amazon.com/images/M/MV5BMWE2OWQ0MTMtZGFjNS00NWNkLTlkMmMtODMxNjZmOTJjNGY5XkEyXkFqcGdeQXVyNjg2NDk5NDI@._V1_SY150_CR4,0,101,150_.jpg",
    "imdbID": "7539210",
    "languages": "Tamil",
    "title": "Sangu Chakkaram",
    "kind": "movie",
    "directors": "Maarison",
    "writers": "Maarison",
    "producers": [
        "V.S. Rajkumar",
        "K. Sathish"
    ],
    "composers": "Shabir",
    "cinematographers": "G. Ravikannan",
    "editors": "Vijay Velukutty",
    "sound department": [
        "Nagavenkatakumar",
        "Narayanan Sp"
    ],
    "stunts": "Dhilip Subbarayan",
    "writer": "Maarison",
    "director": "Maarison",
    "production companies": [
        "Cinemawala Pictures",
        "Leo Vision"
    ],
    "distributors": [
        "Sunshine Studios",
        "Sun TV"
    ],
    "plot": "Kids Satire Fantasy Horror."
}