{
    "id": "12182904",
    "localized title": "Once Again",
    "cast": [
        "Lee Min-Jung",
        "Ho-jin Chun",
        "Hwa-yeon Cha",
        "Lee Sang-Yeob",
        "Yun-a Oh",
        "Dae-hwan Oh",
        "Cho-hee Lee",
        "Lee Jeong-eun",
        "Ji-won Baek",
        "Bo-yeon Kim"
    ],
    "genres": [
        "Comedy",
        "Drama",
        "Romance"
    ],
    "runtimes": "35",
    "countries": "South Korea",
    "country codes": "kr",
    "language codes": "ko",
    "color info": "Color",
    "aspect ratio": "1080i(HDTV)",
    "sound mix": "Dolby Digital",
    "certificates": [
        "Australia:M",
        "Indonesia:13+::(self-applied)",
        "Philippines:13+::(self-applied)",
        "Singapore:PG13",
        "South Korea:15",
        "Turkey:13+::(self-applied)"
    ],
    "cover url": "https://m.media-amazon.com/images/M/MV5BNzY0NjI2ZjUtODU5OS00OTFlLWIyMTYtNDc3ZWZlMTY3ZmZmXkEyXkFqcGdeQXVyMTE3MDM4MzE3._V1_SX101_CR0,0,101,150_.jpg",
    "imdbID": "12182904",
    "plot outline": "Song Young Dal and Jang Ok Boon have been married for many years and they have 4 children: Joon Sun, Ga Hee, Na Hee and Da Hee. Third child Na Hee is a doctor and she works with her husband Doctor Kyu Jin at the same hospital. They fell in love during their medical school days and got married, but their marriage life is not doing very well. Meanwhile, the first child Joon Sun and the second child Ga Hee are both divorcees and live with their parents. The youngest child Da Hee struggles as an intern at a company.",
    "languages": "Korean",
    "title": "Once Again",
    "kind": "tv series",
    "series years": "2020-",
    "akas": [
        "Han Beon Danyeowasseubnida (South Korea)",
        "I Have Been There Once (World-wide, English title)",
        "\u0645\u0631\u0629 \u062b\u0627\u0646\u064a\u0629 (United Arab Emirates)"
    ],
    "seasons": "1",
    "writer": "Hee-Seung Yang",
    "production companies": [
        "Bon Factory Worldwide",
        "Studio Dragon"
    ],
    "distributors": [
        "KBS2",
        "Korean Broadcasting System (KBS)",
        "Netflix"
    ],
    "plot": [
        "\"_Once Again_ (qv)\" is a story about love and family based on the Song Family, who never have a peaceful day.",
        "Song Young Dal and Jang Ok Boon have been married for many years and they have 4 children: Joon Sun, Ga Hee, Na Hee and Da Hee. Third child Na Hee is a doctor and she works with her husband Doctor Kyu Jin at the same hospital. They fell in love during their medical school days and got married, but their marriage life is not doing very well. Meanwhile, the first child Joon Sun and the second child Ga Hee are both divorcees and live with their parents. The youngest child Da Hee struggles as an intern at a company."
    ]
}