{
    "id": "12915964",
    "localized title": "Satya Gang",
    "cast": [
        "Akshita",
        "Sathvik Eshwar",
        "Harshita Panwar",
        "Prathyush",
        "Harishitha Singh"
    ],
    "genres": "Drama",
    "runtimes": "134",
    "countries": "India",
    "country codes": "in",
    "language codes": "te",
    "color info": "Color",
    "original air date": "06 Apr 2018 (India)",
    "imdbID": "12915964",
    "languages": "Telugu",
    "title": "Satya Gang",
    "kind": "movie",
    "directors": "Prabhas Nimmala",
    "akas": "Satya Gang (India)",
    "director": "Prabhas Nimmala",
    "production companies": "Sidda Yogi Creations"
}