{
    "id": "6007628",
    "localized title": "Nagesh Thiraiyarangam",
    "cast": [
        "Aari Arujunan",
        "Ashna Zaveri",
        "B. Abhilash",
        "Masoom Shankar",
        "Latha",
        "Sithara",
        "Kaali Venkat",
        "Manobala",
        "Ramachandran Durairaj",
        "Anil Murali",
        "RajeshB."
    ],
    "genres": "Horror",
    "runtimes": "128",
    "countries": "India",
    "country codes": "in",
    "language codes": "ta",
    "color info": "Color",
    "certificates": [
        "India:UA",
        "Singapore:NC16"
    ],
    "original air date": "16 Feb 2018 (India)",
    "cover url": "https://m.media-amazon.com/images/M/MV5BYjRhYWViOTAtN2Y1Ni00OTAyLThjZTEtNzI4NjAzNDZmM2M2XkEyXkFqcGdeQXVyMzMxMDUzNTk@._V1_SY150_CR4,0,101,150_.jpg",
    "imdbID": "6007628",
    "languages": "Tamil",
    "title": "Nagesh Thiraiyarangam",
    "kind": "movie",
    "directors": "Mohamad Issack",
    "writers": "Mohamad Issack",
    "producers": "Rajendra m Rajan",
    "composers": "Srikanth Deva",
    "cinematographers": [
        "E.J. Nauzad",
        "M.S. Prabhu"
    ],
    "editors": "S. Devaraj",
    "art directors": "Ramalingam",
    "production managers": "B. Abhilash",
    "assistant directors": [
        "Shahul Hameed",
        "Martin Raja",
        "RajeshB.",
        "Ramakrishnan",
        "Jagan Set"
    ],
    "sound department": "Renjith Venugopal",
    "visual effects": "Trotsky Marudu",
    "music department": [
        "Uma Devi",
        "Sajith Anderson Raj"
    ],
    "writer": "Mohamad Issack",
    "director": "Mohamad Issack",
    "production companies": "Transindian Media & Entertainment Private",
    "distributors": "Sunshine Studios",
    "plot": "A real estate broker tries to sell a theater which is haunted by a ghost."
}