{
    "id": "1579532",
    "localized title": "Bobbili Simham",
    "cast": [
        "Nandamuri Balakrishna",
        "Brahmanandam",
        "Kongara Jaggaiah",
        "Meena",
        "Kaikala Satyanarayana",
        "Sharada"
    ],
    "genres": "Drama",
    "runtimes": "126",
    "countries": "India",
    "country codes": "in",
    "language codes": "te",
    "color info": "Color",
    "original air date": "23 Sep 1994 (India)",
    "imdbID": "1579532",
    "plot outline": "Bobbili Simham is a 1994 Telugu-language action drama film, produced by Trivikram Rao under the Vijayalakshmi Art Pictures banner and directed by A. Kodandarami Reddy. It stars Nandamuri Balakrishna, Meena, Roja in the lead roles and music composed by M. M. Keeravani.",
    "languages": "Telugu",
    "title": "Bobbili Simham",
    "kind": "movie",
    "directors": "A. Kodandarami Reddy",
    "writers": [
        "Vijayendra Prasad",
        "",
        "Paruchuri Venkateswara Rao",
        "Gopalakrishna Paruchuri"
    ],
    "akas": "Bobbili Simham (India)",
    "writer": [
        "Vijayendra Prasad",
        "Paruchuri Venkateswara Rao",
        "Gopalakrishna Paruchuri"
    ],
    "director": "A. Kodandarami Reddy",
    "plot": "_Bobbili Simham_ (qv) is a 1994 Telugu-language action drama film, produced by Trivikram Rao under the Vijayalakshmi Art Pictures banner and directed by A. Kodandarami Reddy. It stars Nandamuri Balakrishna, Meena, Roja in the lead roles and music composed by M. M. Keeravani."
}