{
    "id": "3089922",
    "localized title": "Image",
    "cast": [
        "Mounir Ait Hamou",
        "San\u00e2a Alaoui",
        "Gene Bervoets",
        "Charlotte Anne Bongaerts",
        "Fabrice Boutique",
        "Jawad Elbe",
        "Yassine Fadel",
        "Wouter Hendrickx",
        "Manou Kersting",
        "Nabil Mallat",
        "Charley Pasteleurs",
        "Jeroen Van der Ven",
        "Stijn Van Opstal",
        "Geert Van Rampelberg",
        "Laura Verlinden"
    ],
    "genres": "Thriller",
    "runtimes": "87",
    "countries": "Belgium",
    "country codes": "be",
    "language codes": [
        "nl",
        "fr"
    ],
    "color info": "Color",
    "certificates": "United Kingdom:15",
    "original air date": "05 Nov 2014 (Belgium)",
    "cover url": "https://m.media-amazon.com/images/M/MV5BNzQxNzQxNjk5NV5BMl5BanBnXkFtZTgwNTI4MTU0MzE@._V1_SY150_CR2,0,101,150_.jpg",
    "imdbID": "3089922",
    "languages": [
        "Dutch",
        "French"
    ],
    "title": "Image",
    "kind": "movie",
    "directors": [
        "Adil El Arbi",
        "Bilall Fallah"
    ],
    "writers": [
        "Adil El Arbi",
        "",
        "Bilall Fallah",
        "",
        "Bram Renders"
    ],
    "producers": [
        "Peter Bouckaert",
        "Kobe Van Steenberghe",
        "Hendrik Verth\u00e9"
    ],
    "composers": "Hannes De Maeyer",
    "cinematographers": "Robrecht Heyvaert",
    "editors": [
        "Adil El Arbi",
        "Bilall Fallah"
    ],
    "editorial department": [
        "Tom Mulder",
        "Frederik Sonck"
    ],
    "art directors": "Stijn Verhoeven",
    "costume designers": "Nina Caspari",
    "make up department": "Dorien Biesmans",
    "assistant directors": [
        "Julien Clip",
        "Nicola Oliverio",
        "Kobe Van Steenberghe"
    ],
    "art department": [
        "Zo\u00eb Jaspaert",
        "Miriam Matthys"
    ],
    "sound department": [
        "Gedeon Depauw",
        "Wout Frigne",
        "Maarten Leemans",
        "Thomas Vertongen"
    ],
    "special effects": "Arne Normon",
    "visual effects": [
        "Hans Lettany",
        "Tom Mulder",
        "Stefan Rycken",
        "Kosmas Stergiou",
        "Makis Stergiou"
    ],
    "camera department": [
        "Robin Herinckx",
        "Wim Swinnen",
        "Steven Vanvolsem",
        "Jeroen Verdonck"
    ],
    "animation department": "Amira Daoudi",
    "location management": [
        "Steve De Roover",
        "Rachid El Mousati",
        "Kevin Hoed",
        "Annemie Janssens"
    ],
    "music department": [
        "Rutger Arents",
        "Tobias Hess"
    ],
    "miscellaneous": "Hans Lettany",
    "akas": "\u0418\u0437\u043e\u0431\u0440\u0430\u0436\u0435\u043d\u0438\u0435 (Russia)",
    "writer": [
        "Adil El Arbi",
        "Bilall Fallah",
        "Bram Renders"
    ],
    "director": [
        "Adil El Arbi",
        "Bilall Fallah"
    ],
    "production companies": [
        "A Team Productions",
        "Eyeworks Film & TV Drama"
    ],
    "distributors": [
        "Kinepolis Film Distribution (KFD)",
        "Kinepolis Film Distribution (KFD)"
    ],
    "other companies": [
        "ACE Image Factory",
        "Lites Lighting",
        "Lites"
    ],
    "plot": "When Eva, a young journalist, films a documentary about the mean streets in Brussels she soon gets involved in the life of a young Moroccan guy."
}